dotlang/__init__.py
dotlang/__main__.py
dotlang/dotlang.py
dotlang-0.0.1.dist-info/LICENSE
dotlang-0.0.1.dist-info/METADATA
dotlang-0.0.1.dist-info/WHEEL
dotlang-0.0.1.dist-info/top_level.txt
dotlang-0.0.1.dist-info/RECORD
